[
  {
    "parroquia": "GONZALO DÍAZ DE PINEDA",
    "id": 1020,
    "votos": 113,
    "candidato": "Lasso Mendoza Guillermo Alberto Santiago",
    "value": 27.43
  },
  {
    "parroquia": "LINARES",
    "id": 2180,
    "votos": 36,
    "candidato": "Lasso Mendoza Guillermo Alberto Santiago",
    "value": 19.57
  },
  {
    "parroquia": "OYACACHI",
    "id": 2640,
    "votos": 23,
    "candidato": "Lasso Mendoza Guillermo Alberto Santiago",
    "value": 5.46
  },
  {
    "parroquia": "SANTA ROSA DE QUIJOS",
    "id": 3745,
    "votos": 261,
    "candidato": "Lasso Mendoza Guillermo Alberto Santiago",
    "value": 33.76
  },
  {
    "parroquia": "SARDINAS",
    "id": 3790,
    "votos": 113,
    "candidato": "Lasso Mendoza Guillermo Alberto Santiago",
    "value": 33.73
  },
  {
    "parroquia": "EL CHACO",
    "id": 5510,
    "votos": 1185,
    "candidato": "Lasso Mendoza Guillermo Alberto Santiago",
    "value": 33.64
  }
]