[
    {
        "parroquia": "CUMBARATZA",
        "id": 720,
        "votos": 7,
        "candidato": "Paúl Carrasco",
        "value": 0.31
    },
    {
        "parroquia": "GUADALUPE",
        "id": 1390,
        "votos": 4,
        "candidato": "Paúl Carrasco",
        "value": 0.20
    },
    {
        "parroquia": "SAN CARLOS DE LAS MINAS",
        "id": 1770,
        "votos": 3,
        "candidato": "Paúl Carrasco",
        "value": 0.26
    },
    {
        "parroquia": "LA VICTORIA DE IMBANA",
        "id": 2155,
        "votos": 0,
        "candidato": "Paúl Carrasco",
        "fill": "#ced4da"
    },
    {
        "parroquia": "SABANILLA",
        "id": 3260,
        "votos": 0,
        "candidato": "Paúl Carrasco",
        "fill": "#ced4da"
    },
    {
        "parroquia": "TIMBARA",
        "id": 4010,
        "votos": 4,
        "candidato": "Paúl Carrasco",
        "value": 0.36
    },
    {
        "parroquia": "ZAMORA",
        "id": 6305,
        "votos": 29,
        "candidato": "Paúl Carrasco",
        "value": 0.30
    },
    {
        "parroquia": "EL LIMON",
        "id": 6840,
        "votos": 0,
        "candidato": "Paúl Carrasco",
        "fill": "#ced4da"
    }
]