[
    {
        "parroquia": "SANTA MARIANITA",
        "id": 1800,
        "votos": 5,
        "candidato": "Giovanny Andrade",
        "value": 0.27
    },
    {
        "parroquia": "SAN LORENZO",
        "id": 3550,
        "votos": 2,
        "candidato": "Giovanny Andrade",
        "value": 0.09
    },
    {
        "parroquia": "LOS ESTEROS",
        "id": 5570,
        "votos": 26,
        "candidato": "Giovanny Andrade",
        "value": 0.12
    },
    {
        "parroquia": "MANTA",
        "id": 5635,
        "votos": 57,
        "candidato": "Giovanny Andrade",
        "value": 0.11
    },
    {
        "parroquia": "SAN MATEO",
        "id": 6135,
        "votos": 10,
        "candidato": "Giovanny Andrade",
        "value": 0.36
    },
    {
        "parroquia": "TARQUI",
        "id": 6155,
        "votos": 83,
        "candidato": "Giovanny Andrade",
        "value": 0.17
    },
    {
        "parroquia": "ELOY ALFARO",
        "id": 6745,
        "votos": 35,
        "candidato": "Giovanny Andrade",
        "value": 0.16
    }
]