[
  {
    "parroquia": "DURENO",
    "id": 1045,
    "votos": 29,
    "candidato": "Bucaram Pulley Abdala Jaime",
    "value": 1.72
  },
  {
    "parroquia": "EL ENO",
    "id": 1285,
    "votos": 51,
    "candidato": "Bucaram Pulley Abdala Jaime",
    "value": 1.47
  },
  {
    "parroquia": "PACAYÁCU",
    "id": 1290,
    "votos": 102,
    "candidato": "Bucaram Pulley Abdala Jaime",
    "value": 2.61
  },
  {
    "parroquia": "GENERAL FARFÁN",
    "id": 1330,
    "votos": 52,
    "candidato": "Bucaram Pulley Abdala Jaime",
    "value": 1.96
  },
  {
    "parroquia": "SANTA CECILIA",
    "id": 1790,
    "votos": 47,
    "candidato": "Bucaram Pulley Abdala Jaime",
    "value": 2.01
  },
  {
    "parroquia": "JAMBELÍ",
    "id": 1795,
    "votos": 13,
    "candidato": "Bucaram Pulley Abdala Jaime",
    "value": 0.95
  },
  {
    "parroquia": "10 DE AGOSTO",
    "id": 4625,
    "votos": 14,
    "candidato": "Bucaram Pulley Abdala Jaime",
    "value": 2.67
  },
  {
    "parroquia": "NUEVA LOJA",
    "id": 5710,
    "votos": 1018,
    "candidato": "Bucaram Pulley Abdala Jaime",
    "value": 2.72
  }
]