[
    {
        "partido": "PARTIDO UNIDAD REPUBLICANA PARTIDO CONSERVADOR ECUATORIANO",
        "candidato": "SIXTO DURÁN-BALLÉN CORDOVEZ",
        "provincia": "AZUAY",
        "votos": 65849,
        "value": 39.41
    },
    {
        "partido": "PARTIDO UNIDAD REPUBLICANA PARTIDO CONSERVADOR ECUATORIANO",
        "candidato": "SIXTO DURÁN-BALLÉN CORDOVEZ",
        "provincia": "BOLIVAR",
        "votos": 13668,
        "value": 29.45
    },
    {
        "partido": "PARTIDO UNIDAD REPUBLICANA PARTIDO CONSERVADOR ECUATORIANO",
        "candidato": "SIXTO DURÁN-BALLÉN CORDOVEZ",
        "provincia": "CAÑAR",
        "votos": 16619,
        "value": 30.10
    },
    {
        "partido": "PARTIDO UNIDAD REPUBLICANA PARTIDO CONSERVADOR ECUATORIANO",
        "candidato": "SIXTO DURÁN-BALLÉN CORDOVEZ",
        "provincia": "CARCHI",
        "votos": 21409,
        "value": 38.50
    },
    {
        "partido": "PARTIDO UNIDAD REPUBLICANA PARTIDO CONSERVADOR ECUATORIANO",
        "candidato": "SIXTO DURÁN-BALLÉN CORDOVEZ",
        "provincia": "COTOPAXI",
        "votos": 30229,
        "value": 32.41
    },
    {
        "partido": "PARTIDO UNIDAD REPUBLICANA PARTIDO CONSERVADOR ECUATORIANO",
        "candidato": "SIXTO DURÁN-BALLÉN CORDOVEZ",
        "provincia": "CHIMBORAZO",
        "votos": 40434,
        "value": 34.65
    },
    {
        "partido": "PARTIDO UNIDAD REPUBLICANA PARTIDO CONSERVADOR ECUATORIANO",
        "candidato": "SIXTO DURÁN-BALLÉN CORDOVEZ",
        "provincia": "EL ORO",
        "votos": 36753,
        "value": 24.10
    },
    {
        "partido": "PARTIDO UNIDAD REPUBLICANA PARTIDO CONSERVADOR ECUATORIANO",
        "candidato": "SIXTO DURÁN-BALLÉN CORDOVEZ",
        "provincia": "ESMERALDAS",
        "votos": 14552,
        "value": 16.68
    },
    {
        "partido": "PARTIDO UNIDAD REPUBLICANA PARTIDO CONSERVADOR ECUATORIANO",
        "candidato": "SIXTO DURÁN-BALLÉN CORDOVEZ",
        "provincia": "GUAYAS",
        "votos": 167379,
        "value": 17.35
    },
    {
        "partido": "PARTIDO UNIDAD REPUBLICANA PARTIDO CONSERVADOR ECUATORIANO",
        "candidato": "SIXTO DURÁN-BALLÉN CORDOVEZ",
        "provincia": "IMBABURA",
        "votos": 34900,
        "value": 34.63
    },
    {
        "partido": "PARTIDO UNIDAD REPUBLICANA PARTIDO CONSERVADOR ECUATORIANO",
        "candidato": "SIXTO DURÁN-BALLÉN CORDOVEZ",
        "provincia": "LOJA",
        "votos": 32478,
        "value": 26.37
    },
    {
        "partido": "PARTIDO UNIDAD REPUBLICANA PARTIDO CONSERVADOR ECUATORIANO",
        "candidato": "SIXTO DURÁN-BALLÉN CORDOVEZ",
        "provincia": "LOS RIOS",
        "votos": 31596,
        "value": 19.82
    },
    {
        "partido": "PARTIDO UNIDAD REPUBLICANA PARTIDO CONSERVADOR ECUATORIANO",
        "candidato": "SIXTO DURÁN-BALLÉN CORDOVEZ",
        "provincia": "MANABI",
        "votos": 93621,
        "value": 29.57
    },
    {
        "partido": "PARTIDO UNIDAD REPUBLICANA PARTIDO CONSERVADOR ECUATORIANO",
        "candidato": "SIXTO DURÁN-BALLÉN CORDOVEZ",
        "provincia": "MOR.STGO.",
        "votos": 7374,
        "value": 32.94
    },
    {
        "partido": "PARTIDO UNIDAD REPUBLICANA PARTIDO CONSERVADOR ECUATORIANO",
        "candidato": "SIXTO DURÁN-BALLÉN CORDOVEZ",
        "provincia": "NAPO",
        "votos": 7253,
        "value": 27.28
    },
    {
        "partido": "PARTIDO UNIDAD REPUBLICANA PARTIDO CONSERVADOR ECUATORIANO",
        "candidato": "SIXTO DURÁN-BALLÉN CORDOVEZ",
        "provincia": "PASTAZA",
        "votos": 5509,
        "value": 43.54
    },
    {
        "partido": "PARTIDO UNIDAD REPUBLICANA PARTIDO CONSERVADOR ECUATORIANO",
        "candidato": "SIXTO DURÁN-BALLÉN CORDOVEZ",
        "provincia": "PICHINCHA",
        "votos": 402844,
        "value": 55.16
    },
    {
        "partido": "PARTIDO UNIDAD REPUBLICANA PARTIDO CONSERVADOR ECUATORIANO",
        "candidato": "SIXTO DURÁN-BALLÉN CORDOVEZ",
        "provincia": "TUNGURAHUA",
        "votos": 56924,
        "value": 38.95
    },
    {
        "partido": "PARTIDO UNIDAD REPUBLICANA PARTIDO CONSERVADOR ECUATORIANO",
        "candidato": "SIXTO DURÁN-BALLÉN CORDOVEZ",
        "provincia": "ZAMORA CH.",
        "votos": 3664,
        "value": 21.38
    },
    {
        "partido": "PARTIDO UNIDAD REPUBLICANA PARTIDO CONSERVADOR ECUATORIANO",
        "candidato": "SIXTO DURÁN-BALLÉN CORDOVEZ",
        "provincia": "GALAPAGOS",
        "votos": 1351,
        "value": 35.99
    },
    {
        "partido": "PARTIDO UNIDAD REPUBLICANA PARTIDO CONSERVADOR ECUATORIANO",
        "candidato": "SIXTO DURÁN-BALLÉN CORDOVEZ",
        "provincia": "SUCUMBIOS",
        "votos": 4732,
        "value": 24.92
    }
]