[
  {
    "parroquia": "FEBRES CORDERO",
    "id": 5355,
    "votos": 131034,
    "candidato": "Moreno Garces Lenin Boltaire",
    "value": 50.04
  },
  {
    "parroquia": "XIMENA",
    "id": 6265,
    "votos": 167150,
    "candidato": "Moreno Garces Lenin Boltaire",
    "value": 50.29
  },
  {
    "parroquia": "TARQUI",
    "id": 6150,
    "votos": 172314,
    "candidato": "Moreno Garces Lenin Boltaire",
    "value": 45.11
  },
  {
    "parroquia": "PASCUALES",
    "id": 6405,
    "votos": 96919,
    "candidato": "Moreno Garces Lenin Boltaire",
    "value": 60.36
  },
  {
    "parroquia": "JUAN GÓMEZ RENDÓN",
    "id": 1870,
    "votos": 3398,
    "candidato": "Moreno Garces Lenin Boltaire",
    "value": 54.98
  },
  {
    "parroquia": "MORRO",
    "id": 2470,
    "votos": 1206,
    "candidato": "Moreno Garces Lenin Boltaire",
    "value": 50.21
  },
  {
    "parroquia": "POSORJA",
    "id": 2940,
    "votos": 9202,
    "candidato": "Moreno Garces Lenin Boltaire",
    "value": 67.62
  },
  {
    "parroquia": "PUNÁ",
    "id": 3030,
    "votos": 3933,
    "candidato": "Moreno Garces Lenin Boltaire",
    "value": 76.15
  },
  {
    "parroquia": "TENGUEL",
    "id": 4120,
    "votos": 4287,
    "candidato": "Moreno Garces Lenin Boltaire",
    "value": 65.12
  },
  {
    "parroquia": "AYACUCHO",
    "id": 5055,
    "votos": 4796,
    "candidato": "Moreno Garces Lenin Boltaire",
    "value": 34.52
  },
  {
    "parroquia": "BOLÍVAR/SAGRARIO",
    "id": 5125,
    "votos": 4718,
    "candidato": "Moreno Garces Lenin Boltaire",
    "value": 41.21
  },
  {
    "parroquia": "CARBO/CONCEPCIÓN",
    "id": 5170,
    "votos": 8632,
    "candidato": "Moreno Garces Lenin Boltaire",
    "value": 39.16
  },
  {
    "parroquia": "GARCÍA MORENO",
    "id": 5380,
    "votos": 17631,
    "candidato": "Moreno Garces Lenin Boltaire",
    "value": 36.93
  },
  {
    "parroquia": "LETAMENDI",
    "id": 5585,
    "votos": 32126,
    "candidato": "Moreno Garces Lenin Boltaire",
    "value": 42.15
  },
  {
    "parroquia": "9 DE OCTUBRE",
    "id": 5695,
    "votos": 3507,
    "candidato": "Moreno Garces Lenin Boltaire",
    "value": 36.69
  },
  {
    "parroquia": "OLMEDO/SAN ALEJO",
    "id": 5720,
    "votos": 4633,
    "candidato": "Moreno Garces Lenin Boltaire",
    "value": 38.68
  },
  {
    "parroquia": "ROCA",
    "id": 5880,
    "votos": 4196,
    "candidato": "Moreno Garces Lenin Boltaire",
    "value": 36.3
  },
  {
    "parroquia": "ROCAFUERTE",
    "id": 5890,
    "votos": 4028,
    "candidato": "Moreno Garces Lenin Boltaire",
    "value": 35.66
  },
  {
    "parroquia": "SUCRE",
    "id": 6095,
    "votos": 5222,
    "candidato": "Moreno Garces Lenin Boltaire",
    "value": 39.66
  },
  {
    "parroquia": "TARQUI",
    "id": 6150,
    "votos": 31394,
    "candidato": "Moreno Garces Lenin Boltaire",
    "value": 34.47
  },
  {
    "parroquia": "URDANETA",
    "id": 6185,
    "votos": 8570,
    "candidato": "Moreno Garces Lenin Boltaire",
    "value": 36.66
  }
]