[
    {
        "canton": 390,
        "candidato": "BUCARAM PULLEY ABDALA JAIME",
        "votos": 119369,
        "value": 63.56
    },
    {
        "canton": 425,
        "candidato": "BUCARAM PULLEY ABDALA JAIME",
        "votos": 2625,
        "value": 1.4
    },
    {
        "canton": 735,
        "candidato": "BUCARAM PULLEY ABDALA JAIME",
        "votos": 2146,
        "value": 1.14
    },
    {
        "canton": 820,
        "candidato": "BUCARAM PULLEY ABDALA JAIME",
        "votos": 14485,
        "value": 7.71
    },
    {
        "canton": 95,
        "candidato": "BUCARAM PULLEY ABDALA JAIME",
        "votos": 683,
        "value": 0.36
    },
    {
        "canton": 125,
        "candidato": "BUCARAM PULLEY ABDALA JAIME",
        "votos": 684,
        "value": 0.36
    },
    {
        "canton": 385,
        "candidato": "BUCARAM PULLEY ABDALA JAIME",
        "votos": 2838,
        "value": 1.51
    },
    {
        "canton": 395,
        "candidato": "BUCARAM PULLEY ABDALA JAIME",
        "votos": 2291,
        "value": 1.22
    },
    {
        "canton": 400,
        "candidato": "BUCARAM PULLEY ABDALA JAIME",
        "votos": 5410,
        "value": 2.88
    },
    {
        "canton": 415,
        "candidato": "BUCARAM PULLEY ABDALA JAIME",
        "votos": 2661,
        "value": 1.42
    },
    {
        "canton": 420,
        "candidato": "BUCARAM PULLEY ABDALA JAIME",
        "votos": 12220,
        "value": 6.51
    },
    {
        "canton": 430,
        "candidato": "BUCARAM PULLEY ABDALA JAIME",
        "votos": 2669,
        "value": 1.42
    },
    {
        "canton": 435,
        "candidato": "BUCARAM PULLEY ABDALA JAIME",
        "votos": 2941,
        "value": 1.57
    },
    {
        "canton": 505,
        "candidato": "BUCARAM PULLEY ABDALA JAIME",
        "votos": 2745,
        "value": 1.46
    },
    {
        "canton": 510,
        "candidato": "BUCARAM PULLEY ABDALA JAIME",
        "votos": 1640,
        "value": 0.87
    },
    {
        "canton": 675,
        "candidato": "BUCARAM PULLEY ABDALA JAIME",
        "votos": 755,
        "value": 0.4
    },
    {
        "canton": 715,
        "candidato": "BUCARAM PULLEY ABDALA JAIME",
        "votos": 2588,
        "value": 1.38
    },
    {
        "canton": 790,
        "candidato": "BUCARAM PULLEY ABDALA JAIME",
        "votos": 937,
        "value": 0.5
    },
    {
        "canton": 835,
        "candidato": "BUCARAM PULLEY ABDALA JAIME",
        "votos": 1198,
        "value": 0.64
    },
    {
        "canton": 870,
        "candidato": "BUCARAM PULLEY ABDALA JAIME",
        "votos": 1876,
        "value": 1.0
    },
    {
        "canton": 890,
        "candidato": "BUCARAM PULLEY ABDALA JAIME",
        "votos": 812,
        "value": 0.43
    },
    {
        "canton": 920,
        "candidato": "BUCARAM PULLEY ABDALA JAIME",
        "votos": 1819,
        "value": 0.97
    },
    {
        "canton": 940,
        "candidato": "BUCARAM PULLEY ABDALA JAIME",
        "votos": 1258,
        "value": 0.67
    },
    {
        "canton": 985,
        "candidato": "BUCARAM PULLEY ABDALA JAIME",
        "votos": 430,
        "value": 0.23
    },
    {
        "canton": 986,
        "candidato": "BUCARAM PULLEY ABDALA JAIME",
        "votos": 716,
        "value": 0.38
    }
]