[
    {
        "id": 590,
        "candidato": "Lasso Guillermo",
        "votos": 4117,
        "value": 20.35
    },
    {
        "id": 595,
        "candidato": "Lasso Guillermo",
        "votos": 1851,
        "value": 20.5918345
    },
    {
        "id": 600,
        "candidato": "Lasso Guillermo",
        "votos": 1048,
        "value": 19.577807
    },
    {
        "id": 605,
        "candidato": "Lasso Guillermo",
        "votos": 1089,
        "value": 21.590008
    },
    {
        "id": 610,
        "candidato": "Lasso Guillermo",
        "votos": 2175,
        "value": 22.324
    },
    {
        "id": 611,
        "candidato": "Lasso Guillermo",
        "votos": 335,
        "value": 12.417
    },
    {
        "id": 615,
        "candidato": "Lasso Guillermo",
        "votos": 1299,
        "value": 32.0
    },
    {
        "id": 795,
        "candidato": "Lasso Guillermo",
        "votos": 255,
        "value": 7.576
    },
    {
        "id": 796,
        "candidato": "Lasso Guillermo",
        "votos": 137,
        "value": 12.1
    },
    {
        "id": 797,
        "candidato": "Lasso Guillermo",
        "votos": 201,
        "value": 6.67
    },
    {
        "id": 925,
        "candidato": "Lasso Guillermo",
        "votos": 304,
        "value": 14.06756
    },
    {
        "id": 926,
        "candidato": "Lasso Guillermo",
        "votos": 312,
        "value": 5.26405
    }
]