[
    {
        "parroquia": "COTUNDO",
        "id": 685,
        "votos": 11,
        "candidato": "Gerson Almeida",
        "value": 0.27
    },
    {
        "parroquia": "SAN PABLO DE USHPAYACU",
        "id": 3605,
        "votos": 1,
        "candidato": "Gerson Almeida",
        "value": 0.05
    },
    {
        "parroquia": "HATUN SUMAKU",
        "id": 4630,
        "votos": 2,
        "candidato": "Gerson Almeida",
        "value": 0.13
    },
    {
        "parroquia": "ARCHIDONA",
        "id": 5070,
        "votos": 58,
        "candidato": "Gerson Almeida",
        "value": 0.58
    }
]