[
    {
        "parroquia": "CHAQUINAL",
        "id": 835,
        "votos": 367,
        "candidato": "Lasso Mendoza Guillermo Alberto Santiago",
        "value": 48.54
    },
    {
        "parroquia": "12 DE DICIEMBRE",
        "id": 1035,
        "votos": 418,
        "candidato": "Lasso Mendoza Guillermo Alberto Santiago",
        "value": 40.86
    },
    {
        "parroquia": "MILAGROS",
        "id": 4545,
        "votos": 466,
        "candidato": "Lasso Mendoza Guillermo Alberto Santiago",
        "value": 38.29
    },
    {
        "parroquia": "PINDAL /FEDERÍCO PÁEZ",
        "id": 5810,
        "votos": 1531,
        "candidato": "Lasso Mendoza Guillermo Alberto Santiago",
        "value": 49.01
    }
]