[
    {
        "id": 260,
        "candidato": "Noboa Alvaro",
        "votos": 6333,
        "value": 2.133
    },
    {
        "id": 265,
        "candidato": "Noboa Alvaro",
        "votos": 548,
        "value": 2.3439
    },
    {
        "id": 270,
        "candidato": "Noboa Alvaro",
        "votos": 307,
        "value": 4.0501
    },
    {
        "id": 275,
        "candidato": "Noboa Alvaro",
        "votos": 294,
        "value": 1.9699
    },
    {
        "id": 280,
        "candidato": "Noboa Alvaro",
        "votos": 317,
        "value": 2.068
    },
    {
        "id": 285,
        "candidato": "Noboa Alvaro",
        "votos": 393,
        "value": 3.3728
    },
    {
        "id": 555,
        "candidato": "Noboa Alvaro",
        "votos": 106,
        "value": 2.1427
    },
    {
        "id": 556,
        "candidato": "Noboa Alvaro",
        "votos": 286,
        "value": 3.3048
    },
    {
        "id": 780,
        "candidato": "Noboa Alvaro",
        "votos": 41,
        "value": 1.8704
    },
    {
        "id": 855,
        "candidato": "Noboa Alvaro",
        "votos": 104,
        "value": 3.8633
    },
    {
        "id": 885,
        "candidato": "Noboa Alvaro",
        "votos": 128,
        "value": 1.4219
    },
    {
        "id": 915,
        "candidato": "Noboa Alvaro",
        "votos": 172,
        "value": 2.5748
    },
    {
        "id": 955,
        "candidato": "Noboa Alvaro",
        "votos": 31,
        "value": 0.8048
    },
    {
        "id": 960,
        "candidato": "Noboa Alvaro",
        "votos": 24,
        "value": 1.1439
    },
    {
        "id": 990,
        "candidato": "Noboa Alvaro",
        "votos": 18,
        "value": 0.8763
    }
]