[
  {
    "parroquia": "LA UNIÓN",
    "id": 1535,
    "votos": 79,
    "candidato": "Lasso Mendoza Guillermo Alberto Santiago",
    "value": 15.52
  },
  {
    "parroquia": "SAN MARTÍN DE PUZHIO",
    "id": 1575,
    "votos": 84,
    "candidato": "Lasso Mendoza Guillermo Alberto Santiago",
    "value": 22.11
  },
  {
    "parroquia": "LUIS GALARZA O. (DELEGSOL)",
    "id": 1585,
    "votos": 60,
    "candidato": "Lasso Mendoza Guillermo Alberto Santiago",
    "value": 11.56
  },
  {
    "parroquia": "PRINCIPAL",
    "id": 2950,
    "votos": 88,
    "candidato": "Lasso Mendoza Guillermo Alberto Santiago",
    "value": 11.72
  },
  {
    "parroquia": "CHORDELEG",
    "id": 6435,
    "votos": 1241,
    "candidato": "Lasso Mendoza Guillermo Alberto Santiago",
    "value": 24.58
  }
]